{"name":"P IGBT","description":"A cursed P IGBT\n\nVmax: 951 V\nImax: 213 A\nt: 1764 ns\nVce(on): 1.967 V","image":"https://cursed-transistors-test.lucasteske.dev/img/trx/1461.jpg","attributes":[{"Name":"Vmax","Unit":"V","Value":951,"Range":[2,2400],"Decimals":0},{"Name":"Imax","Unit":"A","Value":213,"Range":[1,400],"Decimals":0},{"Name":"t","Unit":"ns","Value":1764,"Range":[400,8000],"Decimals":0},{"Name":"Vce(on)","Unit":"V","Value":1.9666667,"Range":[0.1,10],"Decimals":3}],"special":false,"early_adopter":false,"base_color":"#faebd7","transistor":"IGBT","variant":"P"}