{"name":"P IGBT","description":"A cursed P IGBT\n\nVmax: 314 V\nImax: 151 A\nt: 3196 ns\nVce(on): 6.033 V","image":"https://cursed-transistors-test.lucasteske.dev/img/trx/1541.jpg","attributes":[{"Name":"Vmax","Unit":"V","Value":314,"Range":[2,2400],"Decimals":0},{"Name":"Imax","Unit":"A","Value":151,"Range":[1,400],"Decimals":0},{"Name":"t","Unit":"ns","Value":3196,"Range":[400,8000],"Decimals":0},{"Name":"Vce(on)","Unit":"V","Value":6.0333333,"Range":[0.1,10],"Decimals":3}],"special":false,"early_adopter":false,"base_color":"#b0c4de","transistor":"IGBT","variant":"P"}