{"name":"P IGBT","description":"A cursed P IGBT\n\nVmax: 1339 V\nImax: 46 A\nt: 2002 ns\nVce(on): 2.667 V","image":"https://cursed-transistors.lucasteske.dev/img/trx/1892.jpg","attributes":[{"Name":"Vmax","Unit":"V","Value":1339,"Range":[2,2400],"Decimals":0},{"Name":"Imax","Unit":"A","Value":46,"Range":[1,400],"Decimals":0},{"Name":"t","Unit":"ns","Value":2002,"Range":[400,8000],"Decimals":0},{"Name":"Vce(on)","Unit":"V","Value":2.6666667,"Range":[0.1,10],"Decimals":3}],"special":false,"early_adopter":false,"base_color":"#2e8b57","transistor":"IGBT","variant":"P"}