{"name":"PNP BJT","description":"A cursed PNP BJT\n\nVmax: 664 V\nImax: 97 A\nt: 3238 ns\nVce(on): 1 V","image":"https://cursed-transistors-test.lucasteske.dev/img/trx/359.jpg","attributes":[{"Name":"Vmax","Unit":"V","Value":664,"Range":[2,2400],"Decimals":0},{"Name":"Imax","Unit":"A","Value":97,"Range":[1,200],"Decimals":0},{"Name":"t","Unit":"ns","Value":3238,"Range":[100,12000],"Decimals":0},{"Name":"Vce(on)","Unit":"V","Value":1.2,"Range":[0.01,4],"Decimals":3}],"special":false,"early_adopter":false,"base_color":"#ffffff","transistor":"BJT","variant":"PNP"}