{"name":"P MOSFET","description":"A cursed P MOSFET\n\nVmax: 107 V\nImax: 19 A\nt: 365 ns\nRDS(on): 2.28749990 R","image":"https://cursed-transistors-test.lucasteske.dev/img/trx/601.jpg","attributes":[{"Name":"Vmax","Unit":"V","Value":107,"Range":[2,1000],"Decimals":0},{"Name":"Imax","Unit":"A","Value":19,"Range":[1,200],"Decimals":0},{"Name":"t","Unit":"ns","Value":365,"Range":[20,1000],"Decimals":0},{"Name":"RDS(on)","Unit":"R","Value":2.2875,"Range":[0.0001,4],"Decimals":8}],"special":false,"early_adopter":true,"base_color":"#bdb76b","transistor":"MOSFET","variant":"P"}