{"name":"NPN BJT","description":"A cursed NPN BJT\n\nVmax: 392 V\nImax: 40 A\nt: 5022 ns\nVce(on): 0.500 V","image":"https://cursed-transistors-test.lucasteske.dev/img/trx/725.jpg","attributes":[{"Name":"Vmax","Unit":"V","Value":392,"Range":[2,2400],"Decimals":0},{"Name":"Imax","Unit":"A","Value":40,"Range":[1,200],"Decimals":0},{"Name":"t","Unit":"ns","Value":5022,"Range":[100,12000],"Decimals":0},{"Name":"Vce(on)","Unit":"V","Value":0.5,"Range":[0.01,4],"Decimals":3}],"special":false,"early_adopter":true,"base_color":"#eee8aa","transistor":"BJT","variant":"NPN"}