{"name":"P IGBT","description":"A cursed P IGBT\n\nVmax: 1546 V\nImax: 279 A\nt: 1471 ns\nVce(on): 5 V","image":"https://cursed-transistors-test.lucasteske.dev/img/trx/809.jpg","attributes":[{"Name":"Vmax","Unit":"V","Value":1546,"Range":[2,2400],"Decimals":0},{"Name":"Imax","Unit":"A","Value":279,"Range":[1,400],"Decimals":0},{"Name":"t","Unit":"ns","Value":1471,"Range":[400,8000],"Decimals":0},{"Name":"Vce(on)","Unit":"V","Value":4.733333,"Range":[0.1,10],"Decimals":3}],"special":false,"early_adopter":false,"base_color":"#9acd32","transistor":"IGBT","variant":"P"}