{"name":"P IGBT","description":"A cursed P IGBT\n\nVmax: 1455 V\nImax: 108 A\nt: 3237 ns\nVce(on): 2 V","image":"https://cursed-transistors-test.lucasteske.dev/img/trx/810.jpg","attributes":[{"Name":"Vmax","Unit":"V","Value":1455,"Range":[2,2400],"Decimals":0},{"Name":"Imax","Unit":"A","Value":108,"Range":[1,400],"Decimals":0},{"Name":"t","Unit":"ns","Value":3237,"Range":[400,8000],"Decimals":0},{"Name":"Vce(on)","Unit":"V","Value":2.2333333,"Range":[0.1,10],"Decimals":3}],"special":false,"early_adopter":false,"base_color":"#ff0000","transistor":"IGBT","variant":"P"}