{"name":"P MOSFET","description":"A cursed P MOSFET\n\nVmax: 200 V\nImax: 53 A\nt: 352 ns\nRDS(on): 0.76249999 R","image":"https://cursed-transistors-test.lucasteske.dev/img/trx/997.jpg","attributes":[{"Name":"Vmax","Unit":"V","Value":200,"Range":[2,1000],"Decimals":0},{"Name":"Imax","Unit":"A","Value":53,"Range":[1,200],"Decimals":0},{"Name":"t","Unit":"ns","Value":352,"Range":[20,1000],"Decimals":0},{"Name":"RDS(on)","Unit":"R","Value":0.7625,"Range":[0.0001,4],"Decimals":8}],"special":false,"early_adopter":true,"base_color":"#6495ed","transistor":"MOSFET","variant":"P"}